setup.py
pylogHandler/__init__.py
pylogHandler/log_hanlder.py
pylogHandler.egg-info/PKG-INFO
pylogHandler.egg-info/SOURCES.txt
pylogHandler.egg-info/dependency_links.txt
pylogHandler.egg-info/top_level.txt