Metadata-Version: 1.0
Name: pylogHandler
Version: 0.1.4
Summary: renoyuan log
Home-page: https://github.com/yhyPython110/pylogHandler.git
Author: renoyuan
Author-email: renoyuan@foxmail.com
License: MIT Licence
Platform: any
